onex_fabricapi/__init__.py
onex_fabricapi/onex_fabricapi.py
onex_fabricapi/onexfabricapi_pb2.py
onex_fabricapi/onexfabricapi_pb2_grpc.py
onex_fabricapi-0.0.48.dist-info/METADATA
onex_fabricapi-0.0.48.dist-info/WHEEL
onex_fabricapi-0.0.48.dist-info/top_level.txt
onex_fabricapi-0.0.48.dist-info/RECORD
