Metadata-Version: 2.1
Name: onex-fabricapi
Version: 0.0.48
Summary: The Open Network Experiments (ONEx) Python Package
Home-page: https://github.com/open-network-experiments/models
Author: Open Network Experiments (ONEx)
License: MIT
Keywords: onex open network experiments testing automation
Platform: UNKNOWN
Classifier: Development Status :: 3 - Alpha
Classifier: Intended Audience :: Developers
Classifier: Topic :: Software Development :: Testing :: Traffic Generation
Classifier: License :: OSI Approved :: MIT License
Classifier: Programming Language :: Python :: 2.7
Classifier: Programming Language :: Python :: 3
Requires-Python: >=2.7, <4
Requires-Dist: pyyaml
